CHANGELOG.md
LICENSE
MANIFEST.in
README.md
setup.cfg
setup.py
pip_services3_kafka/__init__.py
pip_services3_kafka.egg-info/PKG-INFO
pip_services3_kafka.egg-info/SOURCES.txt
pip_services3_kafka.egg-info/dependency_links.txt
pip_services3_kafka.egg-info/requires.txt
pip_services3_kafka.egg-info/top_level.txt
pip_services3_kafka.egg-info/zip-safe
pip_services3_kafka/build/DefaultKafkaFactory.py
pip_services3_kafka/build/KafkaMessageQueueFactory.py
pip_services3_kafka/build/__init__.py
pip_services3_kafka/connect/IKafkaMessageListener.py
pip_services3_kafka/connect/KafkaConnection.py
pip_services3_kafka/connect/KafkaConnectionResolver.py
pip_services3_kafka/connect/KafkaSubscription.py
pip_services3_kafka/connect/__init__.py
pip_services3_kafka/queues/KafkaMessageQueue.py
pip_services3_kafka/queues/__init__.py
test/build/__init__.py
test/build/test_KafkaMessageQueueFactory.py
test/connect/__init__.py
test/connect/test_KafkaConnection.py
test/connect/test_KafkaConnectionResolver.py
test/queues/MessageQueueFixture.py
test/queues/__init__.py
test/queues/test_KafkaMessageQueue.py